calendar_cli/__init__.py
calendar_cli/cal.py
calendar_cli/config.py
calendar_cli/legacy.py
calendar_cli/metadata.py
calendar_cli/template.py
calendar_cli-1.0.1.data/scripts/calendar-cli
calendar_cli-1.0.1.data/scripts/calendar-cli.py
calendar_cli-1.0.1.dist-info/LICENSE.TXT
calendar_cli-1.0.1.dist-info/METADATA
calendar_cli-1.0.1.dist-info/WHEEL
calendar_cli-1.0.1.dist-info/top_level.txt
calendar_cli-1.0.1.dist-info/RECORD
